{
  "CSK_vs_DC":   { "team1_wins": 6, "team2_wins": 5, "total": 11 },
  "CSK_vs_GT":   { "team1_wins": 4, "team2_wins": 3, "total": 7 },
  "CSK_vs_KKR":  { "team1_wins": 5, "team2_wins": 6, "total": 11 },
  "CSK_vs_LSG":  { "team1_wins": 3, "team2_wins": 3, "total": 6 },
  "CSK_vs_MI":   { "team1_wins": 6, "team2_wins": 7, "total": 13 },
  "CSK_vs_PBKS": { "team1_wins": 6, "team2_wins": 4, "total": 10 },
  "CSK_vs_RCB":  { "team1_wins": 7, "team2_wins": 5, "total": 12 },
  "CSK_vs_RR":   { "team1_wins": 5, "team2_wins": 5, "total": 10 },
  "CSK_vs_SRH":  { "team1_wins": 5, "team2_wins": 5, "total": 10 },
  "DC_vs_GT":    { "team1_wins": 3, "team2_wins": 3, "total": 6 },
  "DC_vs_KKR":   { "team1_wins": 5, "team2_wins": 5, "total": 10 },
  "DC_vs_LSG":   { "team1_wins": 3, "team2_wins": 4, "total": 7 },
  "DC_vs_MI":    { "team1_wins": 4, "team2_wins": 5, "total": 9 },
  "DC_vs_PBKS":  { "team1_wins": 5, "team2_wins": 5, "total": 10 },
  "DC_vs_RCB":   { "team1_wins": 5, "team2_wins": 4, "total": 9 },
  "DC_vs_RR":    { "team1_wins": 4, "team2_wins": 5, "total": 9 },
  "DC_vs_SRH":   { "team1_wins": 5, "team2_wins": 5, "total": 10 },
  "GT_vs_KKR":   { "team1_wins": 3, "team2_wins": 4, "total": 7 },
  "GT_vs_LSG":   { "team1_wins": 4, "team2_wins": 3, "total": 7 },
  "GT_vs_MI":    { "team1_wins": 3, "team2_wins": 3, "total": 6 },
  "GT_vs_PBKS":  { "team1_wins": 3, "team2_wins": 3, "total": 6 },
  "GT_vs_RCB":   { "team1_wins": 3, "team2_wins": 3, "total": 6 },
  "GT_vs_RR":    { "team1_wins": 4, "team2_wins": 3, "total": 7 },
  "GT_vs_SRH":   { "team1_wins": 3, "team2_wins": 3, "total": 6 },
  "KKR_vs_LSG":  { "team1_wins": 4, "team2_wins": 2, "total": 6 },
  "KKR_vs_MI":   { "team1_wins": 5, "team2_wins": 6, "total": 11 },
  "KKR_vs_PBKS": { "team1_wins": 5, "team2_wins": 5, "total": 10 },
  "KKR_vs_RCB":  { "team1_wins": 5, "team2_wins": 4, "total": 9 },
  "KKR_vs_RR":   { "team1_wins": 4, "team2_wins": 4, "total": 8 },
  "KKR_vs_SRH":  { "team1_wins": 5, "team2_wins": 5, "total": 10 },
  "LSG_vs_MI":   { "team1_wins": 3, "team2_wins": 4, "total": 7 },
  "LSG_vs_PBKS": { "team1_wins": 4, "team2_wins": 3, "total": 7 },
  "LSG_vs_RCB":  { "team1_wins": 3, "team2_wins": 3, "total": 6 },
  "LSG_vs_RR":   { "team1_wins": 3, "team2_wins": 4, "total": 7 },
  "LSG_vs_SRH":  { "team1_wins": 3, "team2_wins": 3, "total": 6 },
  "MI_vs_PBKS":  { "team1_wins": 6, "team2_wins": 5, "total": 11 },
  "MI_vs_RCB":   { "team1_wins": 8, "team2_wins": 6, "total": 14 },
  "MI_vs_RR":    { "team1_wins": 5, "team2_wins": 5, "total": 10 },
  "MI_vs_SRH":   { "team1_wins": 5, "team2_wins": 5, "total": 10 },
  "PBKS_vs_RCB": { "team1_wins": 4, "team2_wins": 6, "total": 10 },
  "PBKS_vs_RR":  { "team1_wins": 5, "team2_wins": 5, "total": 10 },
  "PBKS_vs_SRH": { "team1_wins": 5, "team2_wins": 5, "total": 10 },
  "RCB_vs_RR":   { "team1_wins": 5, "team2_wins": 5, "total": 10 },
  "RCB_vs_SRH":  { "team1_wins": 5, "team2_wins": 6, "total": 11 },
  "RR_vs_SRH":   { "team1_wins": 5, "team2_wins": 5, "total": 10 }
}
